LICENSE
MANIFEST.in
README.rst
setup.py
django_simple_seo.egg-info/PKG-INFO
django_simple_seo.egg-info/SOURCES.txt
django_simple_seo.egg-info/dependency_links.txt
django_simple_seo.egg-info/top_level.txt
simple_seo/__init__.py
simple_seo/admin.py
simple_seo/fields.py
simple_seo/models.py
simple_seo/settings.py
simple_seo/tags.py
simple_seo/tests.py
simple_seo/urls.py
simple_seo/views.py
simple_seo/templatetags/__init__.py
simple_seo/templatetags/simple_seo.py